pysnooz/__init__.py
pysnooz/advertisement.py
pysnooz/api.py
pysnooz/commands.py
pysnooz/const.py
pysnooz/device.py
pysnooz/model.py
pysnooz/py.typed
pysnooz/store.py
pysnooz/testing.py
pysnooz/transition.py
pysnooz-0.10.0.dist-info/LICENSE
pysnooz-0.10.0.dist-info/METADATA
pysnooz-0.10.0.dist-info/WHEEL
pysnooz-0.10.0.dist-info/RECORD
