Metadata-Version: 2.1
Name: pysnooz
Version: 0.10.0
Summary: Control SNOOZ white noise machines.
Home-page: https://github.com/AustinBrunkhorst/pysnooz
License: MIT
Author: Austin Brunkhorst
Author-email: pysnooz@alb.dev
Requires-Python: >=3.10,<4.0
Classifier: Development Status :: 4 - Beta
Classifier: Intended Audience :: Developers
Classifier: License :: OSI Approved :: MIT License
Classifier: Natural Language :: English
Classifier: Operating System :: OS Independent
Classifier: Programming Language :: Python :: 3
Classifier: Programming Language :: Python :: 3.10
Classifier: Programming Language :: Python :: 3.11
Classifier: Topic :: Software Development :: Libraries
Requires-Dist: Events (>=0.4,<0.5)
Requires-Dist: bleak (>=0.20.2)
Requires-Dist: bleak-retry-connector (>=3.0.2)
Requires-Dist: bluetooth-sensor-state-data (>=1.5.0)
Requires-Dist: home-assistant-bluetooth (>=1.3.0)
Requires-Dist: transitions (>=0.8.11,<0.9.0)
Project-URL: Bug Tracker, https://github.com/AustinBrunkhorst/pysnooz/issues
Project-URL: Changelog, https://github.com/AustinBrunkhorst/pysnooz/blob/main/CHANGELOG.md
Project-URL: Repository, https://github.com/AustinBrunkhorst/pysnooz
